{
  "auto_save": "1",
  "world_height": 1528,
  "world_width": 1528,
  "world_depth":  6,
  "foliage_count": 12000,
  "room_count": 120,
  "noise_frequency": 0.0100,
  "move_distance": 32,
  "harvest_distance": 8,
  "level_interval": 250,
  "max_hunger": 2000,
  "max_stanima": 5000,
  "max_mana_charge": 500,
  "stanima_deduction_factor": 1.15,
  "hunger_deduction_factor": 1.50,
  "health_regeneration": 0.75,
  "room_max_size": 12,
  "room_min_size": 12,
  "max_structures": 640,
  "room_buffer": 2,
  "room_door_size": 4,
  "world_max_size": 10000,
  "world_infi": "0",
  "generation_timeout": 250,
  "world_buffer": 4,
  "max_foliage": 92000,
  "structure_size": 16
}